Metadata-Version: 1.1
Name: slurppy
Version: 0.0.1
Summary: Light-weight package to manage computationally-intensive processing pipelines using SLURM.
Home-page: https://github.com/christian-oreilly/slurppy.git
Author: Christian O'Reilly
Author-email: christian.oreilly@gmail.com
License: bsd-3-clause
Download-URL: https://github.com/christian-oreilly/slurppy/archive/v0.0.1.tar.gz
Platform: UNKNOWN
Classifier: Development Status :: 3 - Alpha
Classifier: Intended Audience :: Developers
Classifier: Topic :: Software Development
Classifier: License :: OSI Approved
Classifier: Programming Language :: Python :: 3
Classifier: Programming Language :: Python :: 3.5
Classifier: Programming Language :: Python :: 3.6
Classifier: Programming Language :: Python :: 3.7
